README.md
setup.cfg
setup.py
beka/__init__.py
beka/beka.py
beka/bgp_message.py
beka/chopper.py
beka/error.py
beka/event.py
beka/ip.py
beka/packing_tools.py
beka/peering.py
beka/route.py
beka/state_machine.py
beka/stream_server.py
beka/timer.py
beka2.egg-info/PKG-INFO
beka2.egg-info/SOURCES.txt
beka2.egg-info/dependency_links.txt
beka2.egg-info/requires.txt
beka2.egg-info/top_level.txt
test/test_beka.py
test/test_bgp_message.py
test/test_chopper.py
test/test_ip.py
test/test_peering.py
test/test_state_machine.py
test/test_timer.py