Metadata-Version: 1.2
Name: beka2
Version: 0.3.3
Summary: A bare-bones BGP speaker
Home-page: https://github.com/trungdtbk/beka
Author: Sam Russell
Author-email: sam.h.russell@gmail.com
License: Apache2
Keywords: bgp beka routing sdn networking
Platform: UNKNOWN
Classifier: Development Status :: 4 - Beta
Classifier: Intended Audience :: System Administrators
Classifier: License :: OSI Approved :: Apache Software License
Classifier: Programming Language :: Python :: 3
Requires-Python: >=3
